Workbook
Name Dienstag: #REF!
Name Donnerstag: #REF!
Name Freitag: #REF!
Name JP: #REF!
Name Mittwoch: #REF!
Name Montag: #REF!
Name Samstag: #REF!

Sheet 粽子销售PICKUP
A1: 粽子销售 26年 VS 25年 同期收入PICK UP（税后_元）
A2: 酒店名称 | B2: 节前38天 | D2: 节前26天 | F2: 节前19天 | H2: 节前9天 | J2: 累计收入
B3: 2025 | C3: 2026 | D3: 2025 | E3: 2026 | F3: 2025 | G3: 2026 | H3: 2025 | I3: 2026 | J3: 2025 | K3: 2026
A4: 香港喜來登 | B4: =VLOOKUP($A4,原表!$A$4:$O$25,COLUMN(C1),0) -> 10261.7 | C4: =VLOOKUP($A4,原表!$A$4:$O$25,COLUMN(D1),0) -> 94983 | D4: =VLOOKUP($A4,原表!$A$4:$O$25,COLUMN(E1),0) -> 46531.88 | E4: =VLOOKUP($A4,原表!$A$4:$O$25,COLUMN(F1),0) -> 0 | F4: =VLOOKUP($A4,原表!$A$4:$O$25,COLUMN(G1),0) -> 84571.2 | G4: =VLOOKUP($A4,原表!$A$4:$O$25,COLUMN(H1),0) -> 0 | H4: =VLOOKUP($A4,原表!$A$4:$O$25,COLUMN(I1),0) -> 93456 | I4: =VLOOKUP($A4,原表!$A$4:$O$25,COLUMN(J1),0) -> 0 | J4: =VLOOKUP(A4,最新数据!$A$4:$H$25,8,0) -> 103301 | K4: =VLOOKUP($A4,原表!$A$4:$O$25,COLUMN(L1),0) -> 0
A5: 佘山艾美 | B5: =VLOOKUP($A5,原表!$A$4:$O$25,COLUMN(C2),0) -> 76390.25 | C5: =VLOOKUP($A5,原表!$A$4:$O$25,COLUMN(D2),0) -> 90335 | D5: =VLOOKUP($A5,原表!$A$4:$O$25,COLUMN(E2),0) -> 104565.47 | E5: =VLOOKUP($A5,原表!$A$4:$O$25,COLUMN(F2),0) -> 0 | F5: =VLOOKUP($A5,原表!$A$4:$O$25,COLUMN(G2),0) -> 131239 | G5: =VLOOKUP($A5,原表!$A$4:$O$25,COLUMN(H2),0) -> 0 | H5: =VLOOKUP($A5,原表!$A$4:$O$25,COLUMN(I2),0) -> 152953.26 | I5: =VLOOKUP($A5,原表!$A$4:$O$25,COLUMN(J2),0) -> 0 | J5: =VLOOKUP(A5,最新数据!$A$4:$H$25,8,0) -> 157588.67 | K5: =VLOOKUP($A5,原表!$A$4:$O$25,COLUMN(L2),0) -> 0
A6: 长沙希尔顿 | B6: =VLOOKUP($A6,原表!$A$4:$O$25,COLUMN(C3),0) -> 157000 | C6: =VLOOKUP($A6,原表!$A$4:$O$25,COLUMN(D3),0) -> 120850 | D6: =VLOOKUP($A6,原表!$A$4:$O$25,COLUMN(E3),0) -> 297052 | E6: =VLOOKUP($A6,原表!$A$4:$O$25,COLUMN(F3),0) -> 0 | F6: =VLOOKUP($A6,原表!$A$4:$O$25,COLUMN(G3),0) -> 845294.69 | G6: =VLOOKUP($A6,原表!$A$4:$O$25,COLUMN(H3),0) -> 0 | H6: =VLOOKUP($A6,原表!$A$4:$O$25,COLUMN(I3),0) -> 1083892 | I6: =VLOOKUP($A6,原表!$A$4:$O$25,COLUMN(J3),0) -> 0 | J6: =VLOOKUP(A6,最新数据!$A$4:$H$25,8,0) -> 1199107 | K6: =VLOOKUP($A6,原表!$A$4:$O$25,COLUMN(L3),0) -> 0
A7: 烟台希尔顿 | B7: =VLOOKUP($A7,原表!$A$4:$O$25,COLUMN(C4),0) -> 28123.89 | C7: =VLOOKUP($A7,原表!$A$4:$O$25,COLUMN(D4),0) -> 53385 | D7: =VLOOKUP($A7,原表!$A$4:$O$25,COLUMN(E4),0) -> 46657 | E7: =VLOOKUP($A7,原表!$A$4:$O$25,COLUMN(F4),0) -> 0 | F7: =VLOOKUP($A7,原表!$A$4:$O$25,COLUMN(G4),0) -> 207865 | G7: =VLOOKUP($A7,原表!$A$4:$O$25,COLUMN(H4),0) -> 0 | H7: =VLOOKUP($A7,原表!$A$4:$O$25,COLUMN(I4),0) -> 330575 | I7: =VLOOKUP($A7,原表!$A$4:$O$25,COLUMN(J4),0) -> 0 | J7: =VLOOKUP(A7,最新数据!$A$4:$H$25,8,0) -> 550827 | K7: =VLOOKUP($A7,原表!$A$4:$O$25,COLUMN(L4),0) -> 0
A8: 武汉希尔顿 | B8: =VLOOKUP($A8,原表!$A$4:$O$25,COLUMN(C5),0) -> 25694 | C8: =VLOOKUP($A8,原表!$A$4:$O$25,COLUMN(D5),0) -> 144015 | D8: =VLOOKUP($A8,原表!$A$4:$O$25,COLUMN(E5),0) -> 111210 | E8: =VLOOKUP($A8,原表!$A$4:$O$25,COLUMN(F5),0) -> 0 | F8: =VLOOKUP($A8,原表!$A$4:$O$25,COLUMN(G5),0) -> 362901.92 | G8: =VLOOKUP($A8,原表!$A$4:$O$25,COLUMN(H5),0) -> 0 | H8: =VLOOKUP($A8,原表!$A$4:$O$25,COLUMN(I5),0) -> 913227 | I8: =VLOOKUP($A8,原表!$A$4:$O$25,COLUMN(J5),0) -> 0 | J8: =VLOOKUP(A8,最新数据!$A$4:$H$25,8,0) -> 1088112 | K8: =VLOOKUP($A8,原表!$A$4:$O$25,COLUMN(L5),0) -> 0
A9: 芜湖希尔顿逸林 | B9: =VLOOKUP($A9,原表!$A$4:$O$25,COLUMN(C6),0) -> 15909 | C9: =VLOOKUP($A9,原表!$A$4:$O$25,COLUMN(D6),0) -> 265486 | D9: =VLOOKUP($A9,原表!$A$4:$O$25,COLUMN(E6),0) -> 724172 | E9: =VLOOKUP($A9,原表!$A$4:$O$25,COLUMN(F6),0) -> 0 | F9: =VLOOKUP($A9,原表!$A$4:$O$25,COLUMN(G6),0) -> 728417 | G9: =VLOOKUP($A9,原表!$A$4:$O$25,COLUMN(H6),0) -> 0 | H9: =VLOOKUP($A9,原表!$A$4:$O$25,COLUMN(I6),0) -> 808858 | I9: =VLOOKUP($A9,原表!$A$4:$O$25,COLUMN(J6),0) -> 0 | J9: =VLOOKUP(A9,最新数据!$A$4:$H$25,8,0) -> 909554.87 | K9: =VLOOKUP($A9,原表!$A$4:$O$25,COLUMN(L6),0) -> 0
A10: 泰州茂御 | B10: =VLOOKUP($A10,原表!$A$4:$O$25,COLUMN(C7),0) -> 7436 | C10: =VLOOKUP($A10,原表!$A$4:$O$25,COLUMN(D7),0) -> 2900 | D10: =VLOOKUP($A10,原表!$A$4:$O$25,COLUMN(E7),0) -> 76162 | E10: =VLOOKUP($A10,原表!$A$4:$O$25,COLUMN(F7),0) -> 0 | F10: =VLOOKUP($A10,原表!$A$4:$O$25,COLUMN(G7),0) -> 79866 | G10: =VLOOKUP($A10,原表!$A$4:$O$25,COLUMN(H7),0) -> 0 | H10: =VLOOKUP($A10,原表!$A$4:$O$25,COLUMN(I7),0) -> 110615 | I10: =VLOOKUP($A10,原表!$A$4:$O$25,COLUMN(J7),0) -> 0 | J10: =VLOOKUP(A10,最新数据!$A$4:$H$25,8,0) -> 247566 | K10: =VLOOKUP($A10,原表!$A$4:$O$25,COLUMN(L7),0) -> 0
A11: 松江睿选 | B11: =VLOOKUP($A11,原表!$A$4:$O$25,COLUMN(C8),0) -> 512 | C11: =VLOOKUP($A11,原表!$A$4:$O$25,COLUMN(D8),0) -> 0 | D11: =VLOOKUP($A11,原表!$A$4:$O$25,COLUMN(E8),0) -> 2688 | E11: =VLOOKUP($A11,原表!$A$4:$O$25,COLUMN(F8),0) -> 0 | F11: =VLOOKUP($A11,原表!$A$4:$O$25,COLUMN(G8),0) -> 2688 | G11: =VLOOKUP($A11,原表!$A$4:$O$25,COLUMN(H8),0) -> 0 | H11: =VLOOKUP($A11,原表!$A$4:$O$25,COLUMN(I8),0) -> 22246 | I11: =VLOOKUP($A11,原表!$A$4:$O$25,COLUMN(J8),0) -> 0 | J11: =VLOOKUP(A11,最新数据!$A$4:$H$25,8,0) -> 20706 | K11: =VLOOKUP($A11,原表!$A$4:$O$25,COLUMN(L8),0) -> 0
A12: 石狮睿选 | B12: =VLOOKUP($A12,原表!$A$4:$O$25,COLUMN(C9),0) -> 0 | C12: =VLOOKUP($A12,原表!$A$4:$O$25,COLUMN(D9),0) -> 0 | D12: =VLOOKUP($A12,原表!$A$4:$O$25,COLUMN(E9),0) -> 0 | E12: =VLOOKUP($A12,原表!$A$4:$O$25,COLUMN(F9),0) -> 0 | F12: =VLOOKUP($A12,原表!$A$4:$O$25,COLUMN(G9),0) -> 2106 | G12: =VLOOKUP($A12,原表!$A$4:$O$25,COLUMN(H9),0) -> 0 | H12: =VLOOKUP($A12,原表!$A$4:$O$25,COLUMN(I9),0) -> 3160 | I12: =VLOOKUP($A12,原表!$A$4:$O$25,COLUMN(J9),0) -> 0 | J12: =VLOOKUP(A12,最新数据!$A$4:$H$25,8,0) -> 9257 | K12: =VLOOKUP($A12,原表!$A$4:$O$25,COLUMN(L9),0) -> 0
A13: 沈阳希尔顿 | B13: =VLOOKUP($A13,原表!$A$4:$O$25,COLUMN(C10),0) -> 4028 | C13: =VLOOKUP($A13,原表!$A$4:$O$25,COLUMN(D10),0) -> 1584 | D13: =VLOOKUP($A13,原表!$A$4:$O$25,COLUMN(E10),0) -> 8868 | E13: =VLOOKUP($A13,原表!$A$4:$O$25,COLUMN(F10),0) -> 0 | F13: =VLOOKUP($A13,原表!$A$4:$O$25,COLUMN(G10),0) -> 14718 | G13: =VLOOKUP($A13,原表!$A$4:$O$25,COLUMN(H10),0) -> 0 | H13: =VLOOKUP($A13,原表!$A$4:$O$25,COLUMN(I10),0) -> 307977 | I13: =VLOOKUP($A13,原表!$A$4:$O$25,COLUMN(J10),0) -> 0 | J13: =VLOOKUP(A13,最新数据!$A$4:$H$25,8,0) -> 341570 | K13: =VLOOKUP($A13,原表!$A$4:$O$25,COLUMN(L10),0) -> 0
A14: 佘山洲际 | B14: =VLOOKUP($A14,原表!$A$4:$O$25,COLUMN(C11),0) -> 32322 | C14: =VLOOKUP($A14,原表!$A$4:$O$25,COLUMN(D11),0) -> 7240 | D14: =VLOOKUP($A14,原表!$A$4:$O$25,COLUMN(E11),0) -> 54270.796 | E14: =VLOOKUP($A14,原表!$A$4:$O$25,COLUMN(F11),0) -> 0 | F14: =VLOOKUP($A14,原表!$A$4:$O$25,COLUMN(G11),0) -> 85480 | G14: =VLOOKUP($A14,原表!$A$4:$O$25,COLUMN(H11),0) -> 0 | H14: =VLOOKUP($A14,原表!$A$4:$O$25,COLUMN(I11),0) -> 235524 | I14: =VLOOKUP($A14,原表!$A$4:$O$25,COLUMN(J11),0) -> 0 | J14: =VLOOKUP(A14,最新数据!$A$4:$H$25,8,0) -> 287362 | K14: =VLOOKUP($A14,原表!$A$4:$O$25,COLUMN(L11),0) -> 0
A15: 绍兴双店 | B15: =VLOOKUP($A15,原表!$A$4:$O$25,COLUMN(C12),0) -> 4590 | C15: =VLOOKUP($A15,原表!$A$4:$O$25,COLUMN(D12),0) -> 25787 | D15: =VLOOKUP($A15,原表!$A$4:$O$25,COLUMN(E12),0) -> 21562 | E15: =VLOOKUP($A15,原表!$A$4:$O$25,COLUMN(F12),0) -> 0 | F15: =VLOOKUP($A15,原表!$A$4:$O$25,COLUMN(G12),0) -> 81341 | G15: =VLOOKUP($A15,原表!$A$4:$O$25,COLUMN(H12),0) -> 0 | H15: =VLOOKUP($A15,原表!$A$4:$O$25,COLUMN(I12),0) -> 281954 | I15: =VLOOKUP($A15,原表!$A$4:$O$25,COLUMN(J12),0) -> 0 | J15: =VLOOKUP(A15,最新数据!$A$4:$H$25,8,0) -> 396245 | K15: =VLOOKUP($A15,原表!$A$4:$O$25,COLUMN(L12),0) -> 0
... A25: 成都龙泉驿睿选 | B25: =VLOOKUP($A25,原表!$A$4:$O$25,COLUMN(C22),0) -> 1984 | C25: =VLOOKUP($A25,原表!$A$4:$O$25,COLUMN(D22),0) -> 1221 | D25: =VLOOKUP($A25,原表!$A$4:$O$25,COLUMN(E22),0) -> 3126 | E25: =VLOOKUP($A25,原表!$A$4:$O$25,COLUMN(F22),0) -> 0 | F25: =VLOOKUP($A25,原表!$A$4:$O$25,COLUMN(G22),0) -> 4584 | G25: =VLOOKUP($A25,原表!$A$4:$O$25,COLUMN(H22),0) -> 0 | H25: =VLOOKUP($A25,原表!$A$4:$O$25,COLUMN(I22),0) -> 19424 | I25: =VLOOKUP($A25,原表!$A$4:$O$25,COLUMN(J22),0) -> 0 | J25: =VLOOKUP(A25,最新数据!$A$4:$H$25,8,0) -> 28809 | K25: =VLOOKUP($A25,原表!$A$4:$O$25,COLUMN(L22),0) -> 0
A26: 合计 | B26: =SUM(B4:B25) -> 385680.74 | C26: =SUM(C4:C25) -> 1235728 | D26: =SUM(D4:D25) -> 1747396.2 | E26: =SUM(E4:E25) -> 0 | F26: =SUM(F4:F25) -> 3593461.8 | G26: =SUM(G4:G25) -> 0 | H26: =SUM(H4:H25) -> 6366957.5 | I26: =SUM(I4:I25) -> 0 | ... K26: =SUM(K4:K25) -> 0

Sheet 最新数据
A2: 酒店名称 | B2: =粽子销售PICKUP!B2:C2 -> 节前38天 | F2: 目标销售额 | G2: 目标完成率 | H2: 去年销售额 | I2: 去年完成率
B3: 25年销售额 | C3: 26年销售额 | D3: 同比增减额 | E3: 同比增减%
A4: =粽子销售PICKUP!A4 -> 香港喜來登 | B4: =粽子销售PICKUP!B4 -> 10261.7 | C4: =粽子销售PICKUP!C4 -> 94983 | D4: =C4-B4 -> 84721.3 | E4: =C4/B4-1 -> 8.2560687 | F4: =VLOOKUP(A4,原表!$A$4:$B$25,2,0) -> 120000 | G4: =C4/F4 -> 0.791525 | H4: =VLOOKUP(A4,'2026年 粽子礼盒销售汇总'!$B$4:$N$27,7,0) -> 103301 | I4: =C4/H4 -> 0.91947803
A5: =粽子销售PICKUP!A5 -> 佘山艾美 | B5: =粽子销售PICKUP!B5 -> 76390.25 | C5: =粽子销售PICKUP!C5 -> 90335 | D5: =C5-B5 -> 13944.75 | E5: =C5/B5-1 -> 0.1825462 | F5: =VLOOKUP(A5,原表!$A$4:$B$25,2,0) -> 173348 | G5: =C5/F5 -> 0.52111937 | H5: =VLOOKUP(A5,'2026年 粽子礼盒销售汇总'!$B$4:$N$27,7,0) -> 157588.67 | I5: =C5/H5 -> 0.57323283
A6: =粽子销售PICKUP!A6 -> 长沙希尔顿 | B6: =粽子销售PICKUP!B6 -> 157000 | C6: =粽子销售PICKUP!C6 -> 120850 | D6: =C6-B6 -> -36150 | E6: =C6/B6-1 -> -0.23025478 | F6: =VLOOKUP(A6,原表!$A$4:$B$25,2,0) -> 1250069 | G6: =C6/F6 -> 0.096674664 | H6: =VLOOKUP(A6,'2026年 粽子礼盒销售汇总'!$B$4:$N$27,7,0) -> 1199107 | I6: =C6/H6 -> 0.10078333
A7: =粽子销售PICKUP!A7 -> 烟台希尔顿 | B7: =粽子销售PICKUP!B7 -> 28123.89 | C7: =粽子销售PICKUP!C7 -> 53385 | D7: =C7-B7 -> 25261.11 | E7: =C7/B7-1 -> 0.89820825 | F7: =VLOOKUP(A7,原表!$A$4:$B$25,2,0) -> 605910 | G7: =C7/F7 -> 0.088107145 | H7: =VLOOKUP(A7,'2026年 粽子礼盒销售汇总'!$B$4:$N$27,7,0) -> 550827 | I7: =C7/H7 -> 0.096917907
A8: =粽子销售PICKUP!A8 -> 武汉希尔顿 | B8: =粽子销售PICKUP!B8 -> 25694 | C8: =粽子销售PICKUP!C8 -> 144015 | D8: =C8-B8 -> 118321 | E8: =C8/B8-1 -> 4.6050051 | F8: =VLOOKUP(A8,原表!$A$4:$B$25,2,0) -> 1088112 | G8: =C8/F8 -> 0.1323531 | H8: =VLOOKUP(A8,'2026年 粽子礼盒销售汇总'!$B$4:$N$27,7,0) -> 1088112 | I8: =C8/H8 -> 0.1323531
A9: =粽子销售PICKUP!A9 -> 芜湖希尔顿逸林 | B9: =粽子销售PICKUP!B9 -> 15909 | C9: =粽子销售PICKUP!C9 -> 265486 | D9: =C9-B9 -> 249577 | E9: =C9/B9-1 -> 15.687787 | F9: =VLOOKUP(A9,原表!$A$4:$B$25,2,0) -> 945837 | G9: =C9/F9 -> 0.28068896 | H9: =VLOOKUP(A9,'2026年 粽子礼盒销售汇总'!$B$4:$N$27,7,0) -> 909554.87 | I9: =C9/H9 -> 0.29188563
A10: =粽子销售PICKUP!A10 -> 泰州茂御 | B10: =粽子销售PICKUP!B10 -> 7436 | C10: =粽子销售PICKUP!C10 -> 2900 | D10: =C10-B10 -> -4536 | E10: =C10/B10-1 -> -0.61000538 | F10: =VLOOKUP(A10,原表!$A$4:$B$25,2,0) -> 272323 | G10: =C10/F10 -> 0.010649119 | H10: =VLOOKUP(A10,'2026年 粽子礼盒销售汇总'!$B$4:$N$27,7,0) -> 247566 | I10: =C10/H10 -> 0.011714048
A11: =粽子销售PICKUP!A11 -> 松江睿选 | B11: =粽子销售PICKUP!B11 -> 512 | C11: =粽子销售PICKUP!C11 -> 0 | D11: =C11-B11 -> -512 | E11: =C11/B11-1 -> -1 | F11: =VLOOKUP(A11,原表!$A$4:$B$25,2,0) -> 22777 | G11: =C11/F11 -> 0 | H11: =VLOOKUP(A11,'2026年 粽子礼盒销售汇总'!$B$4:$N$27,7,0) -> 20706 | I11: =C11/H11 -> 0
A12: =粽子销售PICKUP!A12 -> 石狮睿选 | B12: =粽子销售PICKUP!B12 -> 0 | C12: =粽子销售PICKUP!C12 -> 0 | D12: =C12-B12 -> 0 | E12: =C12/B12-1 -> #DIV/0! | F12: =VLOOKUP(A12,原表!$A$4:$B$25,2,0) -> 10183 | G12: =C12/F12 -> 0 | H12: =VLOOKUP(A12,'2026年 粽子礼盒销售汇总'!$B$4:$N$27,7,0) -> 9257 | I12: =C12/H12 -> 0
A13: =粽子销售PICKUP!A13 -> 沈阳希尔顿 | B13: =粽子销售PICKUP!B13 -> 4028 | C13: =粽子销售PICKUP!C13 -> 1584 | D13: =C13-B13 -> -2444 | E13: =C13/B13-1 -> -0.60675273 | F13: =VLOOKUP(A13,原表!$A$4:$B$25,2,0) -> 400000 | G13: =C13/F13 -> 0.00396 | H13: =VLOOKUP(A13,'2026年 粽子礼盒销售汇总'!$B$4:$N$27,7,0) -> 341570 | I13: =C13/H13 -> 0.0046374096
A14: =粽子销售PICKUP!A14 -> 佘山洲际 | B14: =粽子销售PICKUP!B14 -> 32322 | C14: =粽子销售PICKUP!C14 -> 7240 | D14: =C14-B14 -> -25082 | E14: =C14/B14-1 -> -0.77600396 | F14: =VLOOKUP(A14,原表!$A$4:$B$25,2,0) -> 316098 | G14: =C14/F14 -> 0.022904289 | H14: =VLOOKUP(A14,'2026年 粽子礼盒销售汇总'!$B$4:$N$27,7,0) -> 287362 | I14: =C14/H14 -> 0.025194702
A15: =粽子销售PICKUP!A15 -> 绍兴双店 | B15: =粽子销售PICKUP!B15 -> 4590 | C15: =粽子销售PICKUP!C15 -> 25787 | D15: =C15-B15 -> 21197 | E15: =C15/B15-1 -> 4.6180828 | F15: =VLOOKUP(A15,原表!$A$4:$B$25,2,0) -> 435870 | G15: =C15/F15 -> 0.059162135 | H15: =VLOOKUP(A15,'2026年 粽子礼盒销售汇总'!$B$4:$N$27,7,0) -> 396245 | I15: =C15/H15 -> 0.065078424
... A25: =粽子销售PICKUP!A25 -> 成都龙泉驿睿选 | B25: =粽子销售PICKUP!B25 -> 1984 | C25: =粽子销售PICKUP!C25 -> 1221 | D25: =C25-B25 -> -763 | E25: =C25/B25-1 -> -0.38457661 | F25: =VLOOKUP(A25,原表!$A$4:$B$25,2,0) -> 31690 | G25: =C25/F25 -> 0.038529505 | H25: =VLOOKUP(A25,'2026年 粽子礼盒销售汇总'!$B$4:$N$27,7,0) -> 28809 | I25: =C25/H25 -> 0.042382589
A26: 合计 | B26: =SUM(B4:B25) -> 385680.74 | C26: =SUM(C4:C25) -> 1235728 | D26: =C26-B26 -> 850047.26 | E26: =C26/B26-1 -> 2.2040179 | F26: =SUM(F4:F25) -> 8942741 | G26: =C26/F26 -> 0.13818224 | H26: =SUM(H4:H25) -> 8126892.8 | I26: =C26/H26 -> 0.15205418

Sheet 经验总结
A2: 酒店名称 | B2: 2025年销售经验“得与失” | C2: 2026年粽子亮点与特色
A3: =粽子销售PICKUP!A4 -> 香港喜來登
A4: =粽子销售PICKUP!A5 -> 佘山艾美
A5: =粽子销售PICKUP!A6 -> 长沙希尔顿
A6: =粽子销售PICKUP!A7 -> 烟台希尔顿
A7: =粽子销售PICKUP!A8 -> 武汉希尔顿
A8: =粽子销售PICKUP!A9 -> 芜湖希尔顿逸林
A9: =粽子销售PICKUP!A10 -> 泰州茂御
A10: =粽子销售PICKUP!A11 -> 松江睿选
A11: =粽子销售PICKUP!A12 -> 石狮睿选
A12: =粽子销售PICKUP!A13 -> 沈阳希尔顿
A13: =粽子销售PICKUP!A14 -> 佘山洲际
A14: =粽子销售PICKUP!A15 -> 绍兴双店
... A24: =粽子销售PICKUP!A25 -> 成都龙泉驿睿选

Sheet 2026年 粽子礼盒销售汇总
A1: 2026年 世茂酒店粽子销售汇总（元）
A2: 序号 | B2: 酒店 | C2: 2026年 计划销售目标 | G2: 2025年 实际销售 | K2: 26年目标 VS 25年实际 | O2: 收入完成%
C3: 计划 盒数 | D3: 收入 （不含税） | E3: 预期 利润 | F3: 单价 | G3: 最终 盒数 | H3: 收入 （不含税） | I3: 实际 利润 | J3: 单价 | K3: 盒数 | L3: 收入 （不含税） | M3: 利润 | N3: 单价
A4: 1 | B4: 牡丹江假日 | C4: 1000 | D4: 140000 | E4: 42000 | F4: =D4/C4 -> 140 | G4: 852 | H4: 90849 | I4: 29072 | J4: =H4/G4 -> 106.63028 | K4: =C4-G4 -> 148 | L4: =D4-H4 -> 49151 | M4: =E4-I4 -> 12928 | N4: =F4-J4 -> 33.369718 | O4: =D4/H4 -> 1.5410186
A5: 2 | B5: 南京希尔顿 | C5: 12000 | D5: 1000000 | E5: 250000 | F5: =D5/C5 -> 83.333333 | G5: 11725 | H5: 771905.25 | I5: 231136.43 | J5: =H5/G5 -> 65.834136 | K5: =C5-G5 -> 275 | L5: =D5-H5 -> 228094.75 | M5: =E5-I5 -> 18863.57 | N5: =F5-J5 -> 17.499197 | O5: =D5/H5 -> 1.2954958
A6: 3 | B6: 沈阳希尔顿 | C6: 4000 | D6: 400000 | E6: 140000 | F6: =D6/C6 -> 100 | G6: 4493 | H6: 341570 | I6: 125099 | J6: =H6/G6 -> 76.022702 | K6: =C6-G6 -> -493 | L6: =D6-H6 -> 58430 | M6: =E6-I6 -> 14901 | N6: =F6-J6 -> 23.977298 | O6: =D6/H6 -> 1.171063
A7: 4 | B7: 香港喜來登 | C7: 1000 | D7: 120000 | E7: 64000 | F7: =D7/C7 -> 120 | G7: 882 | H7: 103301 | I7: 49000 | J7: =H7/G7 -> 117.12132 | K7: =C7-G7 -> 118 | L7: =D7-H7 -> 16699 | M7: =E7-I7 -> 15000 | N7: =F7-J7 -> 2.8786848 | O7: =D7/H7 -> 1.1616538
A8: 5 | B8: 福州洲际 | C8: 5000 | D8: 400000 | E8: 132000 | F8: =D8/C8 -> 80 | G8: 4664 | H8: 350930 | I8: 109925 | J8: =H8/G8 -> 75.242281 | K8: =C8-G8 -> 336 | L8: =D8-H8 -> 49070 | M8: =E8-I8 -> 22075 | N8: =F8-J8 -> 4.7577187 | O8: =D8/H8 -> 1.1398285
A9: 6 | B9: 松江睿选 | C9: 160 | D9: 22000 | E9: 9600 | F9: =D9/C9 -> 137.5 | G9: 141 | H9: 20706 | I9: 8941 | J9: =H9/G9 -> 146.85106 | K9: =C9-G9 -> 19 | L9: =D9-H9 -> 1294 | M9: =E9-I9 -> 659 | N9: =F9-J9 -> -9.3510638 | O9: =D9/H9 -> 1.062494
A10: 7 | B10: 虹桥睿选尚品 | C10: 480 | D10: 58000 | E10: 21000 | F10: =D10/C10 -> 120.83333 | G10: 471 | H10: 55000 | I10: 20193 | J10: =H10/G10 -> 116.77282 | K10: =C10-G10 -> 9 | L10: =D10-H10 -> 3000 | M10: =E10-I10 -> 807 | N10: =F10-J10 -> 4.0605096 | O10: =D10/H10 -> 1.0545455
A11: 8 | B11: 长沙希尔顿 | C11: 18000 | D11: 1250000 | E11: 250000 | F11: =D11/C11 -> 69.444444 | G11: 17800 | H11: 1199107 | I11: 218279 | J11: =H11/G11 -> 67.365562 | K11: =C11-G11 -> 200 | L11: =D11-H11 -> 50893 | M11: =E11-I11 -> 31721 | N11: =F11-J11 -> 2.0788826 | O11: =D11/H11 -> 1.0424424
A12: 9 | B12: 成都龙泉驿睿选 | C12: 200 | D12: 30000 | E12: 13000 | F12: =D12/C12 -> 150 | G12: 164 | H12: 28809 | I12: 12308 | J12: =H12/G12 -> 175.66463 | K12: =C12-G12 -> 36 | L12: =D12-H12 -> 1191 | M12: =E12-I12 -> 692 | N12: =F12-J12 -> -25.664634 | O12: =D12/H12 -> 1.0413412
A13: 10 | B13: 佘山艾美 | C13: 800 | D13: 163892.56 | E13: 65557.2 | F13: =D13/C13 -> 204.8657 | G13: 678 | H13: 157588.67 | I13: 46764.16 | J13: =H13/G13 -> 232.43167 | K13: =C13-G13 -> 122 | L13: =D13-H13 -> 6303.89 | M13: =E13-I13 -> 18793.04 | N13: =F13-J13 -> -27.565967 | O13: =D13/H13 -> 1.0400022
A14: 11 | B14: 杭州艾美 | C14: 3200 | D14: 270000 | E14: 80000 | F14: =D14/C14 -> 84.375 | G14: 2894 | H14: 260110 | I14: 73038.16 | J14: =H14/G14 -> 89.87906 | K14: =C14-G14 -> 306 | L14: =D14-H14 -> 9890 | M14: =E14-I14 -> 6961.84 | N14: =F14-J14 -> -5.5040601 | O14: =D14/H14 -> 1.0380224
A15: 12 | B15: 绍兴双店 | C15: 4500 | D15: 410000 | E15: 205000 | F15: =D15/C15 -> 91.111111 | G15: 3913 | H15: 396245 | I15: 205818.95 | J15: =H15/G15 -> 101.26374 | K15: =C15-G15 -> 587 | L15: =D15-H15 -> 13755 | M15: =E15-I15 -> -818.95 | N15: =F15-J15 -> -10.152625 | O15: =D15/H15 -> 1.0347134
... A25: 22 | B25: 泰州茂御 | C25: 800 | D25: 134400 | E25: 52000 | F25: =D25/C25 -> 168 | G25: 1260 | H25: 247566 | I25: 53818 | J25: =H25/G25 -> 196.48095 | K25: =C25-G25 -> -460 | L25: =D25-H25 -> -113166 | M25: =E25-I25 -> -1818 | N25: =F25-J25 -> -28.480952 | O25: =D25/H25 -> 0.54288553
C27: =SUM(C4:C25) -> 102490 | D27: =SUM(D4:D25) -> 8435482.6 | E27: =SUM(E4:E25) -> 2750457.2 | F27: =D27/C27 -> 82.305421 | G27: =SUM(G4:G25) -> 102824 | H27: =SUM(H4:H25) -> 8126892.8 | I27: =SUM(I4:I25) -> 2574993.1 | J27: =H27/G27 -> 79.036925 | K27: =C27-G27 -> -334 | L27: =D27-H27 -> 308589.77 | M27: =E27-I27 -> 175464.12 | N27: =F27-J27 -> 3.2684955 | O27: =D27/H27 -> 1.0379714

Sheet 原表
A1: 粽子销售 26年 VS 25年 同期收入PICK UP（税后_元）
A2: 酒店 | B2: 2026年收入目标 （+10%） | C2: 节前38天 | E2: 节前26天 | G2: 节前19天 | I2: 节前9天 | K2: 累计收入 | M2: 同期 完成度% （100%） | N2: 26年实际收入 VS 25年实际收入 完成度% | O2: 26年实际收入 VS 26年收入目标 完成度%
C3: 25年(4.25) | D3: 26年(5.13) | E3: 25年(5.5) | F3: 26年(5.25） | G3: 25年(5.12) | H3: 26年(6.1） | I3: 25年(5.22) | J3: 26年(6.10） | K3: 25年(5.31) | L3: 26年(6.19）
A4: 香港喜來登 | B4: 120000 | C4: 10261.7 | D4: 94983 | E4: 46531.88 | F4: 0 | G4: 84571.2 | H4: 0 | I4: 93456 | J4: 0 | K4: 126966 | L4: 0 | M4: =D4/C4 -> 9.2560687 | N4: =D4/K4 -> 0.74809792 | O4: =D4/B4 -> 0.791525
A5: 佘山艾美 | B5: 173348 | C5: 76390.25 | D5: 90335 | E5: 104565.47 | F5: 0 | G5: 131239 | H5: 0 | I5: 152953.26 | J5: 0 | K5: 157588 | L5: 0 | M5: =D5/C5 -> 1.1825462 | N5: =D5/K5 -> 0.57323527 | O5: =D5/B5 -> 0.52111937
A6: 长沙希尔顿 | B6: 1250069 | C6: 157000 | D6: 120850 | E6: 297052 | F6: 0 | G6: 845294.69 | H6: 0 | I6: 1083892 | J6: 0 | K6: 1083892 | L6: 0 | M6: =D6/C6 -> 0.76974522 | N6: =D6/K6 -> 0.11149635 | O6: =D6/B6 -> 0.096674664
A7: 烟台希尔顿 | B7: 605910 | C7: 28123.89 | D7: 53385 | E7: 46657 | F7: 0 | G7: 207865 | H7: 0 | I7: 330575 | J7: 0 | K7: 570761 | L7: 0 | M7: =D7/C7 -> 1.8982082 | N7: =D7/K7 -> 0.09353302 | O7: =D7/B7 -> 0.088107145
A8: 武汉希尔顿 | B8: 1088112 | C8: 25694 | D8: 144015 | E8: 111210 | F8: 0 | G8: 362901.92 | H8: 0 | I8: 913227 | J8: 0 | K8: 1082590 | L8: 0 | M8: =D8/C8 -> 5.6050051 | N8: =D8/K8 -> 0.1330282 | O8: =D8/B8 -> 0.1323531
A9: 芜湖希尔顿逸林 | B9: 945837 | C9: 15909 | D9: 265486 | E9: 724172 | F9: 0 | G9: 728417 | H9: 0 | I9: 808858 | J9: 0 | K9: 909183 | L9: 0 | M9: =D9/C9 -> 16.687787 | N9: =D9/K9 -> 0.29200502 | O9: =D9/B9 -> 0.28068896
A10: 泰州茂御 | B10: 272323 | C10: 7436 | D10: 2900 | E10: 76162 | F10: 0 | G10: 79866 | H10: 0 | I10: 110615 | J10: 0 | K10: 160299.12 | L10: 0 | M10: =D10/C10 -> 0.38999462 | N10: =D10/K10 -> 0.018091179 | O10: =D10/B10 -> 0.010649119
A11: 松江睿选 | B11: 22777 | C11: =128*4 -> 512 | D11: 0 | E11: 2688 | F11: 0 | G11: 2688 | H11: 0 | I11: 22246 | J11: 0 | K11: 23526 | L11: 0 | M11: =D11/C11 -> 0 | N11: =D11/K11 -> 0 | O11: =D11/B11 -> 0
A12: 石狮睿选 | B12: 10183 | C12: 0 | D12: 0 | E12: 0 | F12: 0 | G12: 2106 | H12: 0 | I12: 3160 | J12: 0 | K12: 3160 | L12: 0 | M12: =D12/C12 -> #DIV/0! | N12: =D12/K12 -> 0 | O12: =D12/B12 -> 0
A13: 沈阳希尔顿 | B13: 400000 | C13: 4028 | D13: 1584 | E13: 8868 | F13: 0 | G13: 14718 | H13: 0 | I13: 307977 | J13: 0 | K13: 385967 | L13: 0 | M13: =D13/C13 -> 0.39324727 | N13: =D13/K13 -> 0.0041039778 | O13: =D13/B13 -> 0.00396
A14: 佘山洲际 | B14: 316098 | C14: 32322 | D14: 7240 | E14: 54270.796 | F14: 0 | G14: 85480 | H14: 0 | I14: 235524 | J14: 0 | K14: 235524 | L14: 0 | M14: =D14/C14 -> 0.22399604 | N14: =D14/K14 -> 0.030739967 | O14: =D14/B14 -> 0.022904289
A15: 绍兴双店 | B15: 435870 | C15: 4590 | D15: 25787 | E15: 21562 | F15: 0 | G15: 81341 | H15: 0 | I15: 281954 | J15: 0 | K15: 394853 | L15: 0 | M15: =D15/C15 -> 5.6180828 | N15: =D15/K15 -> 0.065307849 | O15: =D15/B15 -> 0.059162135
A16: 上海康莱德 | B16: 216414 | C16: 3500 | D16: 27139 | E16: 52842 | F16: 0 | G16: 91590 | H16: 0 | I16: 151692 | J16: 0 | K16: 218934 | L16: 0 | M16: =D16/C16 -> 7.754 | N16: =D16/K16 -> 0.12395973 | O16: =D16/B16 -> 0.12540316
A17: 厦门康莱德 | B17: 492201 | C17: 0 | D17: 780 | E17: 13896 | F17: 0 | G17: 134945 | H17: 0 | I17: 227158.2 | J17: 0 | K17: 505624.7 | L17: 0 | M17: =D17/C17 -> #DIV/0! | N17: =D17/K17 -> 0.0015426462 | O17: =D17/B17 -> 0.0015847184
A18: 宁波双店 | B18: 347083 | C18: 540 | D18: 11300 | E18: 4068 | F18: 0 | G18: 109140 | H18: 0 | I18: 232119 | J18: 0 | K18: 339444 | L18: 0 | M18: =D18/C18 -> 20.925926 | N18: =D18/K18 -> 0.033289733 | O18: =D18/B18 -> 0.032557054
A19: 南京希尔顿 | B19: 1000000 | C19: 2474 | D19: 196331 | E19: 54347 | F19: 0 | G19: 383704 | H19: 0 | I19: 641549 | J19: 0 | K19: 771615 | L19: 0 | M19: =D19/C19 -> 79.35772 | N19: =D19/K19 -> 0.25444166 | O19: =D19/B19 -> 0.196331
A20: 牡丹江假日 | B20: 140000 | C20: 5040 | D20: 24998 | E20: 8580 | F20: 0 | G20: 11760 | H20: 0 | I20: 46814 | J20: 0 | K20: 106127 | L20: 0 | M20: =D20/C20 -> 4.9599206 | N20: =D20/K20 -> 0.23554798 | O20: =D20/B20 -> 0.17855714
A21: 虹桥睿选尚品 | B21: 60500 | C21: 5713 | D21: 0 | E21: 11200 | F21: 0 | G21: 23368 | H21: 0 | I21: 29237 | J21: 0 | K21: 60308 | L21: 0 | M21: =D21/C21 -> 0 | N21: =D21/K21 -> 0 | O21: =D21/B21 -> 0
A22: 杭州艾美 | B22: 286121 | C22: 1146.9 | D22: 26904 | E22: 24966.04 | F22: 0 | G22: 45398 | H22: 0 | I22: 160280 | J22: 0 | K22: 258783.18 | L22: 0 | M22: =D22/C22 -> 23.458017 | N22: =D22/K22 -> 0.10396348 | O22: =D22/B22 -> 0.094030148
A23: 福州洲际 | B23: 400000 | C23: 0 | D23: 73676 | E23: 65282.02 | F23: 0 | G23: 116328 | H23: 0 | I23: 306475 | J23: 0 | K23: 381478 | L23: 0 | M23: =D23/C23 -> #DIV/0! | N23: =D23/K23 -> 0.19313302 | O23: =D23/B23 -> 0.18419
... A25: 成都龙泉驿睿选 | B25: 31690 | C25: 1984 | D25: 1221 | E25: 3126 | F25: 0 | G25: 4584 | H25: 0 | I25: 19424 | J25: 0 | K25: 28809 | L25: 0 | M25: =D25/C25 -> 0.61542339 | N25: =D25/K25 -> 0.042382589 | O25: =D25/B25 -> 0.038529505
B27: =SUM(B4:B25) -> 8942741 | C27: =SUM(C4:C25) -> 385680.74 | D27: =SUM(D4:D25) -> 1235728 | E27: =SUM(E4:E25) -> 1747396.2 | F27: =SUM(F4:F25) -> 0 | G27: =SUM(G4:G25) -> 3593461.8 | H27: =SUM(H4:H25) -> 0 | I27: =SUM(I4:I25) -> 6366957.5 | ... L27: =SUM(L4:L25) -> 0 | M27: =D27/C27 -> 3.2040179 | N27: =D27/K27 -> 0.14373378 | O27: =D27/B27 -> 0.13818224
